README.md
setup.py
mix_nn.egg-info/PKG-INFO
mix_nn.egg-info/SOURCES.txt
mix_nn.egg-info/dependency_links.txt
mix_nn.egg-info/not-zip-safe
mix_nn.egg-info/requires.txt
mix_nn.egg-info/top_level.txt
mixnn/__init__.py
mixnn/__version__.py
mixnn/features.py
mixnn/generator.py
mixnn/metrics.py
mixnn/model.py
mixnn/preprocessing.py
mixnn/utils.py