Metadata-Version: 1.1
Name: mix-nn
Version: 0.1
Summary: High-Level API to train kears NN
Home-page: http://github.com/pmerienne/mix-nn
Author: Pierre Merienne
Author-email: UNKNOWN
License: Apache License, Version 2.0
Download-URL: https://github.com/pmerienne/datalab-utils/archive/0.0.1.tar.gz
Platform: UNKNOWN
